spotless/__init__.py
spotless/app.py
spotless/flask_app_test.py
spotless/main.py
spotless_manager-0.1.2.dist-info/METADATA
spotless_manager-0.1.2.dist-info/WHEEL
spotless_manager-0.1.2.dist-info/entry_points.txt
spotless_manager-0.1.2.dist-info/top_level.txt
spotless_manager-0.1.2.dist-info/RECORD
