Metadata-Version: 2.1
Name: spotless-manager
Version: 0.1.2
Summary: A tool to manage Spotify tracks, detect and delete duplicates
Home-page: https://github.com/felixBorovikov/spotless
Author: Felix Borovikov
Author-email: felixborovikov@gmail.com
License: UNKNOWN
Platform: UNKNOWN
Classifier: Programming Language :: Python :: 3
Classifier: License :: OSI Approved :: MIT License
Classifier: Operating System :: OS Independent
Requires-Dist: requests
Requires-Dist: flask
Requires-Dist: spotipy
Requires-Dist: tqdm
